botfolio/__init__.py
botfolio/exchange/__init__.py
botfolio/exchange/ftx.py
botfolio-0.1.6.dist-info/LICENSE
botfolio-0.1.6.dist-info/METADATA
botfolio-0.1.6.dist-info/WHEEL
botfolio-0.1.6.dist-info/top_level.txt
botfolio-0.1.6.dist-info/RECORD
