Metadata-Version: 2.1
Name: botfolio
Version: 0.1.6
Summary: A set of libraries for botfolio
Home-page: https://github.com/dextervip/botfolio-library
Author: Rafael Amorim
Author-email: email@rafaelamorim.me
License: GNU General Public License v3
Keywords: botfolio
Platform: UNKNOWN
Classifier: Development Status :: 2 - Pre-Alpha
Classifier: Intended Audience :: Developers
Classifier: License :: OSI Approved :: GNU General Public License v3 (GPLv3)
Classifier: Natural Language :: English
Classifier: Programming Language :: Python :: 3
Classifier: Programming Language :: Python :: 3.6
Classifier: Programming Language :: Python :: 3.7
Classifier: Programming Language :: Python :: 3.8
Requires-Python: >=3.6
License-File: LICENSE
Requires-Dist: requests
Requires-Dist: ciso8601
